pyquarks/__init__.py
pyquarks/main.py
pyquarks/binary_trees/__init__.py
pyquarks/binary_trees/binary_trees.py
pyquarks/binary_trees/binary_trees_OOP.py
pyquarks/linked_lists/__init__.py
pyquarks/linked_lists/linked_lists.py
pyquarks/linked_lists/linked_lists_OOP.py
pyquarks/queues/__init__.py
pyquarks/queues/queues.py
pyquarks/queues/queues_OOP.py
pyquarks/searches/__init__.py
pyquarks/searches/binary_search.py
pyquarks/searches/linear_search.py
pyquarks/sorts/__init__.py
pyquarks/sorts/bubble_sort.py
pyquarks/sorts/insertion_sort.py
pyquarks/sorts/lisst_sort.py
pyquarks/stacks/__init__.py
pyquarks/stacks/stacks.py
pyquarks/stacks/stacks_OOP.py
pyquarks-0.0.0.2.dist-info/METADATA
pyquarks-0.0.0.2.dist-info/WHEEL
pyquarks-0.0.0.2.dist-info/top_level.txt
pyquarks-0.0.0.2.dist-info/RECORD
