Metadata-Version: 2.4
Name: pyquarks
Version: 0.0.0.2
Summary: Delivering small additions which matter
Home-page: https://github.com/Prospy006/pyquarks
Author: Prospy006
Dynamic: author
Dynamic: home-page
Dynamic: summary
